toxicdev/__init__.py
toxicdev/tech.py
toxicdev-0.0.1.dist-info/METADATA
toxicdev-0.0.1.dist-info/WHEEL
toxicdev-0.0.1.dist-info/top_level.txt
toxicdev-0.0.1.dist-info/RECORD
