Metadata-Version: 2.4
Name: toxicdev
Version: 0.0.1
Summary: High-speed uploading & downloading toolkit for Telegram using Telethon
Home-page: https://github.com/BtwSiya/toxicdev
Author: Dev
Author-email: TeamToxiclabs@gmail.com
Classifier: Programming Language :: Python :: 3
Classifier: License :: OSI Approved :: MIT License
Classifier: Operating System :: OS Independent
Requires-Python: >=3.6
Requires-Dist: telethon
Requires-Dist: telethon-tgcrypto
Requires-Dist: aiofiles
Dynamic: author
Dynamic: author-email
Dynamic: classifier
Dynamic: description
Dynamic: description-content-type
Dynamic: home-page
Dynamic: requires-dist
Dynamic: requires-python
Dynamic: summary
